langgraph/checkpoint/mongodb/__init__.py
langgraph/checkpoint/mongodb/aio.py
langgraph/checkpoint/mongodb/saver.py
langgraph/checkpoint/mongodb/utils.py
langgraph_checkpoint_mongodb-0.2.2.dist-info/METADATA
langgraph_checkpoint_mongodb-0.2.2.dist-info/WHEEL
langgraph_checkpoint_mongodb-0.2.2.dist-info/RECORD
