Metadata-Version: 2.4
Name: langgraph-checkpoint-mongodb
Version: 0.2.2
Summary: Library with a MongoDB implementation of LangGraph checkpoint saver.
Requires-Python: >=3.10
Requires-Dist: langchain-mongodb<1.0.0
Requires-Dist: langgraph-checkpoint>=3.0.0
Requires-Dist: pymongo<4.16,>=4.12
